scatter/__init__.py
scatter/bench.py
scatter/main.py
scatter/scatter_function.py
scatter/state_manager.py
scatter/utils.py
scatter/cli/__init__.py
scatter/cli/main.py
scatter/cli/sync.py
scatter-0.1.4.dist-info/LICENSE
scatter-0.1.4.dist-info/METADATA
scatter-0.1.4.dist-info/WHEEL
scatter-0.1.4.dist-info/entry_points.txt
scatter-0.1.4.dist-info/top_level.txt
scatter-0.1.4.dist-info/RECORD
