Metadata-Version: 2.2
Name: scatter
Version: 0.1.4
Summary: Live-reloadable remote function management in Python
Author: Sankalp Sanand
Project-URL: Homepage, https://github.com/kessler-frost/scatter
Project-URL: Repository, https://github.com/kessler-frost/scatter
Project-URL: Issues, https://github.com/kessler-frost/scatter/issues
Keywords: redis,lightweight,function,management,live-reload,scatter
Classifier: Development Status :: 3 - Alpha
Classifier: Intended Audience :: Developers
Classifier: Intended Audience :: Science/Research
Classifier: Programming Language :: Python :: 3 :: Only
Classifier: Programming Language :: Python :: 3.10
Classifier: Programming Language :: Python :: 3.11
Classifier: Programming Language :: Python :: 3.12
Classifier: License :: OSI Approved :: MIT License
Requires-Python: >=3.10
License-File: LICENSE
Requires-Dist: cloudpickle>=3.1.1
Requires-Dist: fastapi[standard]>=0.115.8
Requires-Dist: redis[hiredis]>=5.2.1
